{"metadata": {"dbt_schema_version": "https://schemas.getdbt.com/dbt/run-results/v4.json", "dbt_version": "1.5.4", "generated_at": "2023-08-04T15:50:11.658444Z", "invocation_id": "5eb725b2-3a19-4a50-85db-aa5d481dce19", "env": {}}, "results": [{"status": "success", "timing": [{"name": "compile", "started_at": "2023-08-04T15:49:56.567267Z", "completed_at": "2023-08-04T15:49:56.585474Z"}, {"name": "execute", "started_at": "2023-08-04T15:49:56.586713Z", "completed_at": "2023-08-04T15:49:57.452398Z"}], "thread_id": "Thread-95", "execution_time": 1.1420364379882812, "adapter_response": {"_message": "SUCCESS 1", "code": "SUCCESS", "rows_affected": 1, "query_id": "01ae15d5-3201-e21a-0002-24660001fa5e"}, "message": "SUCCESS 1", "failures": null, "unique_id": "model.my_new_project.stg_customers"}, {"status": "success", "timing": [{"name": "compile", "started_at": "2023-08-04T15:49:56.562197Z", "completed_at": "2023-08-04T15:49:56.588087Z"}, {"name": "execute", "started_at": "2023-08-04T15:49:56.589124Z", "completed_at": "2023-08-04T15:49:57.675659Z"}], "thread_id": "Thread-94", "execution_time": 1.3296172618865967, "adapter_response": {"_message": "SUCCESS 1", "code": "SUCCESS", "rows_affected": 1, "query_id": "01ae15d5-3201-e21a-0002-24660001fa62"}, "message": "SUCCESS 1", "failures": null, "unique_id": "model.my_new_project.stg_aisles"}, {"status": "success", "timing": [{"name": "compile", "started_at": "2023-08-04T15:49:57.712247Z", "completed_at": "2023-08-04T15:49:57.730101Z"}, {"name": "execute", "started_at": "2023-08-04T15:49:57.731127Z", "completed_at": "2023-08-04T15:49:58.644089Z"}], "thread_id": "Thread-95", "execution_time": 1.1589670181274414, "adapter_response": {"_message": "SUCCESS 1", "code": "SUCCESS", "rows_affected": 1, "query_id": "01ae15d5-3201-e21a-0002-24660001fa66"}, "message": "SUCCESS 1", "failures": null, "unique_id": "model.my_new_project.stg_department"}, {"status": "success", "timing": [{"name": "compile", "started_at": "2023-08-04T15:49:57.894945Z", "completed_at": "2023-08-04T15:49:57.912351Z"}, {"name": "execute", "started_at": "2023-08-04T15:49:57.913432Z", "completed_at": "2023-08-04T15:49:58.716241Z"}], "thread_id": "Thread-94", "execution_time": 1.0459606647491455, "adapter_response": {"_message": "SUCCESS 1", "code": "SUCCESS", "rows_affected": 1, "query_id": "01ae15d5-3201-e219-0002-24660001db0e"}, "message": "SUCCESS 1", "failures": null, "unique_id": "model.my_new_project.stg_hr_contacts"}, {"status": "success", "timing": [{"name": "compile", "started_at": "2023-08-04T15:49:58.945164Z", "completed_at": "2023-08-04T15:49:58.964282Z"}, {"name": "execute", "started_at": "2023-08-04T15:49:58.965845Z", "completed_at": "2023-08-04T15:49:59.728278Z"}], "thread_id": "Thread-94", "execution_time": 1.1424028873443604, "adapter_response": {"_message": "SUCCESS 1", "code": "SUCCESS", "rows_affected": 1, "query_id": "01ae15d5-3201-e21a-0002-24660001fa6a"}, "message": "SUCCESS 1", "failures": null, "unique_id": "model.my_new_project.stg_hr_employeechurn"}, {"status": "success", "timing": [{"name": "compile", "started_at": "2023-08-04T15:49:58.875630Z", "completed_at": "2023-08-04T15:49:58.894134Z"}, {"name": "execute", "started_at": "2023-08-04T15:49:58.895326Z", "completed_at": "2023-08-04T15:49:59.617332Z"}], "thread_id": "Thread-95", "execution_time": 1.2987885475158691, "adapter_response": {"_message": "SUCCESS 1", "code": "SUCCESS", "rows_affected": 1, "query_id": "01ae15d5-3201-e218-0002-24660001eb46"}, "message": "SUCCESS 1", "failures": null, "unique_id": "model.my_new_project.stg_hr_departments"}, {"status": "success", "timing": [{"name": "compile", "started_at": "2023-08-04T15:50:00.090117Z", "completed_at": "2023-08-04T15:50:00.108768Z"}, {"name": "execute", "started_at": "2023-08-04T15:50:00.110003Z", "completed_at": "2023-08-04T15:50:00.888098Z"}], "thread_id": "Thread-94", "execution_time": 1.0149383544921875, "adapter_response": {"_message": "SUCCESS 1", "code": "SUCCESS", "rows_affected": 1, "query_id": "01ae15d6-3201-e219-0002-24660001db12"}, "message": "SUCCESS 1", "failures": null, "unique_id": "model.my_new_project.stg_hr_employees"}, {"status": "success", "timing": [{"name": "compile", "started_at": "2023-08-04T15:50:00.177320Z", "completed_at": "2023-08-04T15:50:00.194636Z"}, {"name": "execute", "started_at": "2023-08-04T15:50:00.195769Z", "completed_at": "2023-08-04T15:50:00.911959Z"}], "thread_id": "Thread-95", "execution_time": 1.0357036590576172, "adapter_response": {"_message": "SUCCESS 1", "code": "SUCCESS", "rows_affected": 1, "query_id": "01ae15d6-3201-e219-0002-24660001db16"}, "message": "SUCCESS 1", "failures": null, "unique_id": "model.my_new_project.stg_hr_positions"}, {"status": "success", "timing": [{"name": "compile", "started_at": "2023-08-04T15:50:01.108315Z", "completed_at": "2023-08-04T15:50:01.127476Z"}, {"name": "execute", "started_at": "2023-08-04T15:50:01.128662Z", "completed_at": "2023-08-04T15:50:01.941688Z"}], "thread_id": "Thread-94", "execution_time": 1.0501141548156738, "adapter_response": {"_message": "SUCCESS 1", "code": "SUCCESS", "rows_affected": 1, "query_id": "01ae15d6-3201-e21a-0002-24660001fa6e"}, "message": "SUCCESS 1", "failures": null, "unique_id": "model.my_new_project.stg_hr_salaries"}, {"status": "success", "timing": [{"name": "compile", "started_at": "2023-08-04T15:50:01.217267Z", "completed_at": "2023-08-04T15:50:01.246615Z"}, {"name": "execute", "started_at": "2023-08-04T15:50:01.247921Z", "completed_at": "2023-08-04T15:50:02.027119Z"}], "thread_id": "Thread-95", "execution_time": 1.0264840126037598, "adapter_response": {"_message": "SUCCESS 1", "code": "SUCCESS", "rows_affected": 1, "query_id": "01ae15d6-3201-e219-0002-24660001db1a"}, "message": "SUCCESS 1", "failures": null, "unique_id": "model.my_new_project.stg_orders"}, {"status": "success", "timing": [{"name": "compile", "started_at": "2023-08-04T15:50:02.161602Z", "completed_at": "2023-08-04T15:50:02.180165Z"}, {"name": "execute", "started_at": "2023-08-04T15:50:02.181464Z", "completed_at": "2023-08-04T15:50:02.907769Z"}], "thread_id": "Thread-94", "execution_time": 0.9592957496643066, "adapter_response": {"_message": "SUCCESS 1", "code": "SUCCESS", "rows_affected": 1, "query_id": "01ae15d6-3201-e218-0002-24660001eb4a"}, "message": "SUCCESS 1", "failures": null, "unique_id": "model.my_new_project.stg_products"}, {"status": "success", "timing": [{"name": "compile", "started_at": "2023-08-04T15:50:02.247784Z", "completed_at": "2023-08-04T15:50:02.265922Z"}, {"name": "execute", "started_at": "2023-08-04T15:50:02.267275Z", "completed_at": "2023-08-04T15:50:04.133887Z"}], "thread_id": "Thread-95", "execution_time": 2.1119160652160645, "adapter_response": {"_message": "SUCCESS 1", "code": "SUCCESS", "rows_affected": 1, "query_id": "01ae15d6-3201-e218-0002-24660001eb4e"}, "message": "SUCCESS 1", "failures": null, "unique_id": "model.my_new_project.percent_order_status"}, {"status": "success", "timing": [{"name": "compile", "started_at": "2023-08-04T15:50:03.124673Z", "completed_at": "2023-08-04T15:50:03.149773Z"}, {"name": "execute", "started_at": "2023-08-04T15:50:03.150871Z", "completed_at": "2023-08-04T15:50:05.978169Z"}], "thread_id": "Thread-94", "execution_time": 3.0638487339019775, "adapter_response": {"_message": "SUCCESS 1", "code": "SUCCESS", "rows_affected": 1, "query_id": "01ae15d6-3201-e21a-0002-24660001fa72"}, "message": "SUCCESS 1", "failures": null, "unique_id": "model.my_new_project.fct_orders"}, {"status": "success", "timing": [{"name": "compile", "started_at": "2023-08-04T15:50:06.197590Z", "completed_at": "2023-08-04T15:50:06.221549Z"}, {"name": "execute", "started_at": "2023-08-04T15:50:06.222594Z", "completed_at": "2023-08-04T15:50:08.082634Z"}], "thread_id": "Thread-94", "execution_time": 2.1415350437164307, "adapter_response": {"_message": "SUCCESS 1", "code": "SUCCESS", "rows_affected": 1, "query_id": "01ae15d6-3201-e21a-0002-24660001fa76"}, "message": "SUCCESS 1", "failures": null, "unique_id": "model.my_new_project.customer_segmentation"}, {"status": "success", "timing": [{"name": "compile", "started_at": "2023-08-04T15:50:06.192696Z", "completed_at": "2023-08-04T15:50:06.217188Z"}, {"name": "execute", "started_at": "2023-08-04T15:50:06.218313Z", "completed_at": "2023-08-04T15:50:09.182284Z"}], "thread_id": "Thread-95", "execution_time": 3.2040741443634033, "adapter_response": {"_message": "SUCCESS 1", "code": "SUCCESS", "rows_affected": 1, "query_id": "01ae15d6-3201-e219-0002-24660001db1e"}, "message": "SUCCESS 1", "failures": null, "unique_id": "model.my_new_project.customer_analysis"}, {"status": "success", "timing": [{"name": "compile", "started_at": "2023-08-04T15:50:08.342376Z", "completed_at": "2023-08-04T15:50:08.361291Z"}, {"name": "execute", "started_at": "2023-08-04T15:50:08.362359Z", "completed_at": "2023-08-04T15:50:09.644211Z"}], "thread_id": "Thread-94", "execution_time": 1.518153429031372, "adapter_response": {"_message": "SUCCESS 1", "code": "SUCCESS", "rows_affected": 1, "query_id": "01ae15d6-3201-e219-0002-24660001db22"}, "message": "SUCCESS 1", "failures": null, "unique_id": "model.my_new_project.monthly_rev_and_profit"}, {"status": "success", "timing": [{"name": "compile", "started_at": "2023-08-04T15:50:09.400304Z", "completed_at": "2023-08-04T15:50:09.418738Z"}, {"name": "execute", "started_at": "2023-08-04T15:50:09.419807Z", "completed_at": "2023-08-04T15:50:11.220457Z"}], "thread_id": "Thread-95", "execution_time": 2.041032075881958, "adapter_response": {"_message": "SUCCESS 1", "code": "SUCCESS", "rows_affected": 1, "query_id": "01ae15d6-3201-e219-0002-24660001db26"}, "message": "SUCCESS 1", "failures": null, "unique_id": "model.my_new_project.profit_revenue_dept"}, {"status": "success", "timing": [{"name": "compile", "started_at": "2023-08-04T15:50:09.866410Z", "completed_at": "2023-08-04T15:50:09.885918Z"}, {"name": "execute", "started_at": "2023-08-04T15:50:09.888163Z", "completed_at": "2023-08-04T15:50:11.433116Z"}], "thread_id": "Thread-94", "execution_time": 1.7865126132965088, "adapter_response": {"_message": "SUCCESS 1", "code": "SUCCESS", "rows_affected": 1, "query_id": "01ae15d6-3201-e21a-0002-24660001fa7a"}, "message": "SUCCESS 1", "failures": null, "unique_id": "model.my_new_project.rev_from_non_alcoholic"}], "elapsed_time": 16.9247944355011, "args": {"deprecated_env_var_warnings": [], "printer_width": 80, "quiet": false, "indirect_selection": "eager", "log_path": "/usr/src/develop/user-184109/environment-221255/repository-166027/logs", "version_check": true, "use_colors": true, "warn_error_options": {"include": [], "exclude": []}, "use_colors_file": true, "select": [], "print": true, "defer": false, "project_dir": "/usr/src/develop/user-184109/environment-221255/repository-166027", "introspect": true, "vars": {}, "macro_debugging": false, "log_format_file": "debug", "populate_cache": true, "profiles_dir": "/usr/src/dbt-server-shared/.dbt", "static_parser": true, "which": "run", "log_level": "info", "strict_mode": false, "write_json": true, "log_format": "default", "partial_parse": true, "enable_legacy_logger": true, "send_anonymous_usage_stats": true, "exclude": [], "favor_state": false, "full_refresh": true, "cache_selected_only": false, "log_level_file": "debug", "rpc_method": "run"}}